{
	"Panel": {
		"GridSize": {"Rows": 11, "Cols": 11},
		"Grid": [
			{
				"Type": "Hexagon",
				"ColorId": -1,
				"Position": {"Row": 0, "Col": 4}
			},
			{
				"Type": "Square",
				"ColorId": 0,
				"Position": {"Row": 1, "Col": 1}
			},
			{
				"Type": "Sun",
				"ColorId": 0,
				"Position": {"Row": 1, "Col": 5}
			},
			{
				"Type": "Wall",
				"ColorId": -1,
				"Position": {"Row": 1, "Col": 8}
			},
			{
				"Type": "Sun",
				"ColorId": 0,
				"Position": {"Row": 3, "Col": 1}
			},
			{
				"Type": "Wall",
				"ColorId": -1,
				"Position": {"Row": 3, "Col": 2}
			},
			{
				"Type": "Wall",
				"ColorId": -1,
				"Position": {"Row": 3, "Col": 4}
			},
			{
				"Type": "Square",
				"ColorId": 1,
				"Position": {"Row": 3, "Col": 9}
			},
			{
				"Type": "Square",
				"ColorId": 0,
				"Position": {"Row": 5, "Col": 1}
			},
			{
				"Type": "Square",
				"ColorId": 1,
				"Position": {"Row": 5, "Col": 3}
			},
			{
				"Type": "Square",
				"ColorId": 1,
				"Position": {"Row": 5, "Col": 7}
			},
			{
				"Type": "Sun",
				"ColorId": 0,
				"Position": {"Row": 5, "Col": 9}
			},
			{
				"Type": "Hexagon",
				"ColorId": -1,
				"Position": {"Row": 6, "Col": 4}
			},
			{
				"Type": "Hexagon",
				"ColorId": -1,
				"Position": {"Row": 6, "Col": 10}
			},
			{
				"Type": "Sun",
				"ColorId": 0,
				"Position": {"Row": 7, "Col": 1}
			},
			{
				"Type": "Sun",
				"ColorId": 1,
				"Position": {"Row": 7, "Col": 5}
			},
			{
				"Type": "Hexagon",
				"ColorId": -1,
				"Position": {"Row": 9, "Col": 0}
			},
			{
				"Type": "Sun",
				"ColorId": 0,
				"Position": {"Row": 9, "Col": 5}
			},
			{
				"Type": "Sun",
				"ColorId": 1,
				"Position": {"Row": 9, "Col": 7}
			},
			{
				"Type": "Sun",
				"ColorId": 1,
				"Position": {"Row": 9, "Col": 9}
			}
		],
		"Start": {"Row": 10, "Col": 6},
		"End": {"Row": 0, "Col": 0}
	}
}
